bayescurvefit/__init__.py
bayescurvefit/analysis.py
bayescurvefit/bayesfit.py
bayescurvefit/data_classes.py
bayescurvefit/distribution.py
bayescurvefit/execution.py
bayescurvefit/simulation.py
bayescurvefit/utils.py
bayescurvefit-0.6.5.dist-info/METADATA
bayescurvefit-0.6.5.dist-info/WHEEL
bayescurvefit-0.6.5.dist-info/licenses/LICENSE
bayescurvefit-0.6.5.dist-info/RECORD
