Metadata-Version: 2.4
Name: bayescurvefit
Version: 0.6.5
Summary: BayesCurveFit: Enhancing Biological Data Analysis with Robust Curve Fitting and FDR Detection
Author-email: Niu Du <ndu0328@gmail.com>
License: Apache-2.0
License-File: LICENSE
Classifier: License :: OSI Approved :: Apache Software License
Classifier: Operating System :: OS Independent
Classifier: Programming Language :: Python :: 3
Classifier: Programming Language :: Python :: 3.11
Classifier: Programming Language :: Python :: 3.12
Classifier: Programming Language :: Python :: 3.13
Requires-Python: >=3.11
Requires-Dist: emcee==3.1.6
Requires-Dist: matplotlib
Requires-Dist: numpy<2.0.0,>=1.26
Requires-Dist: pandas>=2.0
Requires-Dist: scikit-learn>=1.5.0
Requires-Dist: scipy<1.15.0,>=1.7.1
Requires-Dist: seaborn
Requires-Dist: tqdm
Provides-Extra: dev
Requires-Dist: autoflake; extra == 'dev'
Requires-Dist: black>=22.3.0; extra == 'dev'
Requires-Dist: build; extra == 'dev'
Requires-Dist: flake8>=3.9.2; extra == 'dev'
Requires-Dist: isort>=5.10.1; extra == 'dev'
Requires-Dist: mypy; extra == 'dev'
Requires-Dist: pre-commit; extra == 'dev'
Requires-Dist: pytest; extra == 'dev'
Requires-Dist: twine; extra == 'dev'
